[
  {
    "title": "B_AddAngularDimensionByNode",
    "label": "标注节点角度",
    "link": "/guide/B_AddAngularDimensionByNode",
    "icon": "/media/svgs/med_B_AddAngularDimensionByNode.svg",
    "tags": [
      "标注",
      "曲线"
    ]
  },
  {
    "title": "B_AddAxisNumber",
    "label": "创建轴号",
    "link": "/guide/B_AddAxisNumber",
    "icon": "/media/svgs/med_B_AddAxisNumber.svg",
    "tags": [
      "标注"
    ]
  },
  {
    "title": "B_AddDot",
    "label": "注解点标注",
    "link": "/guide/B_AddDot",
    "icon": "/media/svgs/med_B_AddDot.svg",
    "tags": [
      "标注",
      "物件"
    ]
  },
  {
    "title": "B_AddDotByDistance",
    "label": "距离点标注",
    "link": "/guide/B_AddDotByDistance",
    "icon": "/media/svgs/med_B_AddDotByDistance.svg",
    "tags": [
      "标注",
      "点"
    ]
  },
  {
    "title": "B_AddDotByLength",
    "label": "长度点标注",
    "link": "/guide/B_AddDotByLength",
    "icon": "/media/svgs/med_B_AddDotByLength.svg",
    "tags": [
      "标注",
      "曲线"
    ]
  },
  {
    "title": "B_AddDotByLocation",
    "label": "坐标点标注",
    "link": "/guide/B_AddDotByLocation",
    "icon": "/media/svgs/med_B_AddDotByLocation.svg",
    "tags": [
      "标注",
      "点"
    ]
  },
  {
    "title": "B_AddLinearDimensionBy3Pt",
    "label": "三点线性标注",
    "link": "/guide/B_AddLinearDimensionBy3Pt",
    "icon": "/media/svgs/med_B_AddLinearDimensionBy3Pt.svg",
    "tags": [
      "标注"
    ]
  },
  {
    "title": "B_AddLinearDimensionByArc",
    "label": "标注弧长",
    "link": "/guide/B_AddLinearDimensionByArc",
    "icon": "/media/svgs/med_B_AddLinearDimensionByArc.svg",
    "tags": [
      "标注",
      "曲线"
    ]
  },
  {
    "title": "B_AddLinearDimensionByDiagonal",
    "label": "标注对角线",
    "link": "/guide/B_AddLinearDimensionByDiagonal",
    "icon": "/media/svgs/med_B_AddLinearDimensionByDiagonal.svg",
    "tags": [
      "标注",
      "曲面"
    ]
  },
  {
    "title": "B_AddLinearDimensionByInterior",
    "label": "标注内角边缘",
    "link": "/guide/B_AddLinearDimensionByInterior",
    "icon": "/media/svgs/med_B_AddLinearDimensionByInterior.svg",
    "tags": [
      "标注",
      "曲面"
    ]
  },
  {
    "title": "B_AddLinearDimensionByNaked",
    "label": "标注裸露边缘",
    "link": "/guide/B_AddLinearDimensionByNaked",
    "icon": "/media/svgs/med_B_AddLinearDimensionByNaked.svg",
    "tags": [
      "标注",
      "曲面"
    ]
  },
  {
    "title": "B_AddRadialDimension",
    "label": "标注径向尺寸",
    "link": "/guide/B_AddRadialDimension",
    "icon": "/media/svgs/med_B_AddRadialDimension.svg",
    "tags": [
      "标注",
      "曲线"
    ]
  },
  {
    "title": "B_Area",
    "label": "面积",
    "link": "/guide/B_Area",
    "icon": "/media/svgs/med_B_Area.svg",
    "tags": [
      "分析",
      "统计"
    ]
  },
  {
    "title": "B_CopyLayerToClipboard",
    "label": "复制图层",
    "link": "/guide/B_CopyLayerToClipboard",
    "icon": "/media/svgs/med_B_CopyLayerToClipboard.svg",
    "tags": [
      "图层",
      "工具"
    ]
  },
  {
    "title": "B_CornerPin",
    "label": "边角固定",
    "link": "/guide/B_CornerPin",
    "icon": "/media/svgs/med_B_CornerPin.svg",
    "tags": [
      "变换",
      "曲面"
    ]
  },
  {
    "title": "B_CurveSnap",
    "label": "曲线吸附",
    "link": "/guide/B_CurveSnap",
    "icon": "/media/svgs/med_B_CurveSnap.svg",
    "tags": [
      "变换",
      "曲线"
    ]
  },
  {
    "title": "B_ExportLocation",
    "label": "导出点",
    "link": "/guide/B_ExportLocation",
    "icon": "/media/svgs/med_B_ExportLocation.svg",
    "tags": [
      "点",
      "工具"
    ]
  },
  {
    "title": "B_FindText",
    "label": "查找文本",
    "link": "/guide/B_FindText",
    "icon": "/media/svgs/med_B_FindText.svg",
    "tags": [
      "文字"
    ]
  },
  {
    "title": "B_FindTextFromInsertion",
    "label": "从图块查找文本",
    "link": "/guide/B_FindTextFromInsertion",
    "icon": "/media/svgs/med_B_FindTextFromInsertion.svg",
    "tags": [
      "文字"
    ]
  },
  {
    "title": "B_FitArc",
    "label": "曲线拟弧",
    "link": "/guide/B_FitArc",
    "icon": "/media/svgs/med_B_FitArc.svg",
    "tags": [
      "曲线"
    ]
  },
  {
    "title": "B_GroupByBound",
    "label": "群组（区域）",
    "link": "/guide/B_GroupByBound",
    "icon": "/media/svgs/med_B_GroupByBound.svg",
    "tags": [
      "分组"
    ]
  },
  {
    "title": "B_ImportLayerFromClipboard",
    "label": "导入图层",
    "link": "/guide/B_ImportLayerFromClipboard",
    "icon": "/media/svgs/med_B_ImportLayerFromClipboard.svg",
    "tags": [
      "图层",
      "工具"
    ]
  },
  {
    "title": "B_ImportPoints",
    "label": "导入点",
    "link": "/guide/B_ImportPoints",
    "icon": "/media/svgs/med_B_ImportPoints.svg",
    "tags": [
      "点",
      "工具"
    ]
  },
  {
    "title": "B_LayerFullPath",
    "label": "图层完整路径",
    "link": "/guide/B_LayerFullPath",
    "icon": "/media/svgs/med_B_LayerFullPath.svg",
    "tags": [
      "图层",
      "工具"
    ]
  },
  {
    "title": "B_LayerNameReplace",
    "label": "图层名称替换",
    "link": "/guide/B_LayerNameReplace",
    "icon": "/media/svgs/med_B_LayerNameReplace.svg",
    "tags": [
      "图层"
    ]
  },
  {
    "title": "B_LayerOnlyShow",
    "label": "图层独显",
    "link": "/guide/B_LayerOnlyShow",
    "icon": "/media/svgs/med_B_LayerOnlyShow.svg",
    "tags": [
      "图层"
    ]
  },
  {
    "title": "B_Length",
    "label": "长度",
    "link": "/guide/B_Length",
    "icon": "/media/svgs/med_B_Length.svg",
    "tags": [
      "分析",
      "统计",
      "曲线"
    ]
  },
  {
    "title": "B_Make2D",
    "label": "切剖面",
    "link": "/guide/B_Make2D",
    "icon": "/media/svgs/med_B_Make2D.svg",
    "tags": [
      "曲线"
    ]
  },
  {
    "title": "B_ObjectAttributes",
    "label": "物件属性",
    "link": "/guide/B_ObjectAttributes",
    "icon": "/media/svgs/med_B_ObjectAttributes.svg",
    "tags": [
      "物件"
    ]
  },
  {
    "title": "B_ObjectDrop",
    "label": "物件投送",
    "link": "/guide/B_ObjectDrop",
    "icon": "/media/svgs/med_B_ObjectDrop.svg",
    "tags": [
      "物件",
      "工具"
    ]
  },
  {
    "title": "B_ObjectFilter",
    "label": "物件过滤",
    "link": "/guide/B_ObjectFilter",
    "icon": "/media/svgs/med_B_ObjectFilter.svg",
    "tags": [
      "物件"
    ]
  },
  {
    "title": "B_ObjectNameReplace",
    "label": "物件名称替换",
    "link": "/guide/B_ObjectNameReplace",
    "icon": "/media/svgs/med_B_ObjectNameReplace.svg",
    "tags": [
      "物件"
    ]
  },
  {
    "title": "B_ObjectShare",
    "label": "物件分享",
    "link": "/guide/B_ObjectShare",
    "icon": "/media/svgs/med_B_ObjectShare.svg",
    "tags": [
      "物件",
      "工具"
    ]
  },
  {
    "title": "B_ObjectTable",
    "label": "物件表格",
    "link": "/guide/B_ObjectTable",
    "icon": "/media/svgs/med_B_ObjectTable.svg",
    "tags": [
      "物件"
    ]
  },
  {
    "title": "B_PlanarHeightTest",
    "label": "标注曲面弦高",
    "link": "/guide/B_PlanarHeightTest",
    "icon": "/media/svgs/med_B_PlanarHeightTest.svg",
    "tags": [
      "分析",
      "统计",
      "曲面"
    ]
  },
  {
    "title": "B_Planarization",
    "label": "平面化",
    "link": "/guide/B_Planarization",
    "icon": "/media/svgs/med_B_Planarization.svg",
    "tags": [
      "变换",
      "曲面"
    ]
  },
  {
    "title": "B_Project",
    "label": "拍平",
    "link": "/guide/B_Project",
    "icon": "/media/svgs/med_B_Project.svg",
    "tags": [
      "变换"
    ]
  },
  {
    "title": "B_ResetRtf",
    "label": "重置富文本",
    "link": "/guide/B_ResetRtf",
    "icon": "/media/svgs/med_B_ResetRtf.svg",
    "tags": [
      "文字",
      "工具"
    ]
  },
  {
    "title": "B_Rotate",
    "label": "旋转",
    "link": "/guide/B_Rotate",
    "icon": "/media/svgs/med_B_Rotate.svg",
    "tags": [
      "变换"
    ]
  },
  {
    "title": "B_Scale",
    "label": "缩放",
    "link": "/guide/B_Scale",
    "icon": "/media/svgs/med_B_Scale.svg",
    "tags": [
      "变换"
    ]
  },
  {
    "title": "B_SelBlock",
    "label": "选取图块",
    "link": "/guide/B_SelBlock",
    "icon": "/media/svgs/med_B_SelBlock.svg",
    "tags": [
      "选择"
    ]
  },
  {
    "title": "B_SelEdge",
    "label": "选取边缘",
    "link": "/guide/B_SelEdge",
    "icon": "/media/svgs/med_B_SelEdge-106.svg",
    "tags": [
      "选择",
      "曲面"
    ]
  },
  {
    "title": "B_SelLength",
    "label": "以长度选取曲线",
    "link": "/guide/B_SelLength",
    "icon": "/media/svgs/med_B_SelLength.svg",
    "tags": [
      "选择",
      "曲线"
    ]
  },
  {
    "title": "B_SelObject",
    "label": "选取物件",
    "link": "/guide/B_SelObject",
    "icon": "/media/svgs/med_Object.svg",
    "tags": [
      "选择",
      "物件"
    ]
  },
  {
    "title": "B_SelSimilar",
    "label": "选取相似",
    "link": "/guide/B_SelSimilar",
    "icon": "/media/svgs/med_B_SelSimilar.svg",
    "tags": [
      "选择",
      "物件"
    ]
  },
  {
    "title": "B_SetMacro",
    "label": "设置快捷键",
    "link": "/guide/B_SetMacro",
    "icon": "/media/svgs/med_B_SetMacro.svg",
    "tags": [
      "工具"
    ]
  },
  {
    "title": "B_SetSequence",
    "label": "设置物件顺序",
    "link": "/guide/B_SetSequence",
    "icon": "/media/svgs/med_Object.svg",
    "tags": [
      "物件"
    ]
  },
  {
    "title": "B_Slide",
    "label": "滑动",
    "link": "/guide/B_Slide",
    "icon": "/media/svgs/med_B_Slide.svg",
    "tags": [
      "变换"
    ]
  },
  {
    "title": "B_Text",
    "label": "文本",
    "link": "/guide/B_Text",
    "icon": "/media/svgs/med_B_Text.svg",
    "tags": [
      "文字",
      "工具"
    ]
  },
  {
    "title": "B_ToPolyline",
    "label": "曲线拉直",
    "link": "/guide/B_ToPolyline",
    "icon": "/media/svgs/med_B_ToPolyline.svg",
    "tags": [
      "曲线",
      "变换"
    ]
  },
  {
    "title": "B_UniformDirection",
    "label": "统一方向",
    "link": "/guide/B_UniformDirection",
    "icon": "/media/svgs/med_B_UniformDirection.svg",
    "tags": [
      "变换",
      "曲线",
      "曲面"
    ]
  },
  {
    "title": "B_Volume",
    "label": "体积",
    "link": "/guide/B_Volume",
    "icon": "/media/svgs/med_Analysis.svg",
    "tags": [
      "分析",
      "统计"
    ]
  }
]